{
 "SoundBanksInfo": {
  "Platform": "Windows",
  "BasePlatform": "Windows",
  "SchemaVersion": "16",
  "SoundBankVersion": "154",
  "SoundBanks": [
   {
    "Id": "1207059019",
    "Type": "Event",
    "GUID": "{E6BDD8A8-AD24-4FF0-B7C1-8A9BBDCDCBD4}",
    "Language": "SFX",
    "Hash": "{C7D86EF2-E16E-3641-65CB-0EA29FA9E9DD}",
    "ObjectPath": "Pain_Knight",
    "ShortName": "Pain_Knight",
    "Path": "Event/1207059019.bnk",
    "Media": [
     {
      "Id": "424141051",
      "Language": "SFX",
      "Streaming": "false",
      "Location": "Loose",
      "ShortName": "painh_3.wav",
      "Path": "Media/424141051.wem",
      "CachePath": "D7/{D7544FCB-186B-FE4D-AEFF-14A9F2651563}.wem"
     }
    ],
    "Events": [
     {
      "Id": "1207059019",
      "Name": "Pain_Knight",
      "ObjectPath": "\\Events\\Default Work Unit\\Main\\Pain\\Pain_Knight",
      "GUID": "{E6BDD8A8-AD24-4FF0-B7C1-8A9BBDCDCBD4}",
      "DurationType": "OneShot",
      "DurationMin": "0.44193393",
      "DurationMax": "0.589911",
      "MediaRefs": [
       {
        "Id": "424141051"
       }
      ]
     }
    ]
   }
  ],
  "FileHash": "{F87C9AF4-6AC9-DB01-D529-AF3578DF4A44}"
 }
}